efficientbioai/__init__.py
efficientbioai/compress.py
efficientbioai/inference.py
efficientbioai/onnx2trt.py
efficientbioai/utils.py
efficientbioai/compress_ppl/__init__.py
efficientbioai/compress_ppl/pipeline.py
efficientbioai/compress_ppl/pruner.py
efficientbioai/compress_ppl/quantizer.py
efficientbioai/infer/__init__.py
efficientbioai/infer/base.py
efficientbioai/infer/mmv_im2im.py
efficientbioai/infer/omnipose.py
efficientbioai/infer/backend/__init__.py
efficientbioai/infer/backend/openvino.py
efficientbioai/infer/backend/tensorrt.py
efficientbioai/parse_info/__init__.py
efficientbioai/parse_info/base.py
efficientbioai/parse_info/mmv_im2im.py
efficientbioai/parse_info/omnipose.py
efficientbioai-0.0.6.dist-info/LICENSE
efficientbioai-0.0.6.dist-info/METADATA
efficientbioai-0.0.6.dist-info/WHEEL
efficientbioai-0.0.6.dist-info/top_level.txt
efficientbioai-0.0.6.dist-info/RECORD
